MANIFEST.in
changes.txt
license.txt
readme.md
requirements.py
requirements.txt
setup.py
pi_time.egg-info/PKG-INFO
pi_time.egg-info/SOURCES.txt
pi_time.egg-info/dependency_links.txt
pi_time.egg-info/not-zip-safe
pi_time.egg-info/requires.txt
pi_time.egg-info/top_level.txt
pi_time/laptimer/__init__.py
pi_time/laptimer/__init__.pyc
pi_time/laptimer/admin.py
pi_time/laptimer/admin.pyc
pi_time/laptimer/api.py
pi_time/laptimer/api.pyc
pi_time/laptimer/api_lap.py
pi_time/laptimer/api_lap.pyc
pi_time/laptimer/api_rider.py
pi_time/laptimer/api_rider.pyc
pi_time/laptimer/api_sensor.py
pi_time/laptimer/api_sensor.pyc
pi_time/laptimer/api_session.py
pi_time/laptimer/api_session.pyc
pi_time/laptimer/api_track.py
pi_time/laptimer/api_track.pyc
pi_time/laptimer/api_utils.py
pi_time/laptimer/api_utils.pyc
pi_time/laptimer/compute.py
pi_time/laptimer/compute.pyc
pi_time/laptimer/models.py
pi_time/laptimer/models.pyc
pi_time/laptimer/server.py
pi_time/laptimer/server.pyc
pi_time/laptimer/server2.py
pi_time/laptimer/test_api.py
pi_time/laptimer/test_api.pyc
pi_time/laptimer/test_api_lap.py
pi_time/laptimer/test_api_lap.pyc
pi_time/laptimer/test_api_rider.py
pi_time/laptimer/test_api_rider.pyc
pi_time/laptimer/test_api_sensor.py
pi_time/laptimer/test_api_sensor.pyc
pi_time/laptimer/test_api_session.py
pi_time/laptimer/test_api_session.pyc
pi_time/laptimer/test_api_track.py
pi_time/laptimer/test_api_track.pyc
pi_time/laptimer/test_compute.py
pi_time/laptimer/test_compute.pyc
pi_time/laptimer/test_model.py
pi_time/laptimer/test_model.pyc
pi_time/laptimer/test_server.py
pi_time/laptimer/test_server.pyc
pi_time/laptimer/test_utils.py
pi_time/laptimer/test_utils.pyc
pi_time/laptimer/tests.pyc
pi_time/laptimer/utils.py
pi_time/laptimer/utils.pyc
pi_time/laptimer/views.py
pi_time/laptimer/views.pyc
pi_time/laptimer/templates/laptimer/base.html
pi_time/laptimer/templates/laptimer/home.html
pi_time/pi_time/__init__.py
pi_time/pi_time/__init__.pyc
pi_time/pi_time/settings.py
pi_time/pi_time/settings.pyc
pi_time/pi_time/test_settings.py
pi_time/pi_time/test_settings.pyc
pi_time/pi_time/urls.py
pi_time/pi_time/urls.pyc
pi_time/pi_time/wsgi.py