Metadata-Version: 1.1
Name: pi-time
Version: 0.0.1
Summary: Lap timer running on a solar powered Raspberry Pi.
Home-page: http://github.com/si618/pi-time
Author: Simon McKenna
Author-email: sshnug.si+pi-time@gmail.com
License: GNU General Public License v3 or later (GPLv3+)
Platform: UNKNOWN
Classifier: Development Status :: 2 - Pre-Alpha
Classifier: Environment :: Web Environment
Classifier: Intended Audience :: Other Audience
Classifier: License :: OSI Approved :: GNU General Public License v3 or later (GPLv3+)
Classifier: Operating System :: OS Independent
Classifier: Programming Language :: Python
Classifier: Programming Language :: Python :: 2.7
Classifier: Framework :: Django
